{
  "Fatiha": {
    "url": "https://drive.google.com/uc?id=1buLta6GcJoVlLRGEbFQ4to106ky9nt2v",
    "title": "✮͢ꓸ⃟ꓸ⃟ꓸ✮͢এই সূরা টি মক্কায় অবতীর্ণ এর আয়াত সংখ্যা ｢৭｣ ≛⃝⃪⋆⃝"
  },
  "An Nasr": {
    "url": "https://drive.google.com/uc?id=1gqzaxsRZ-hXpgZOneEEF4b8A8YlETQlq",
    "title": "✮͢ꓸ⃟ꓸ⃟ꓸ✮͢ধর্মীয় গ্রন্থ কুরআনের ｢১১০ ｣তম সূরা। তাফসীরকারীদের সর্বসম্মত অভিমত এই যে সূরাটি মদীনায় অবতীর্ণ এবং এর আয়াত সংখ্যা ｢৩｣টি।≛⃝⃪⋆⃝"
  },
  "Lahab": {
    "url": "https://drive.google.com/uc?id=1gpuggj4QNth8k2RXVppoj92_XteCZRze",
    "title": "✮͢ꓸ⃟ꓸ⃟ꓸ✮͢গ্রন্থ কুরআনের ｢১১১｣ তম সূরা। এর আয়াত সংখ্যা ｢৫｣ এবং সূরাটি মক্কায় অবতীর্ণ হয়েছে।≛⃝⃪⋆⃝"
  },
 "Ikhlas": {
      "url":
"https://drive.google.com/uc?id=1gpGpBsH-lIDqYVo8jzpzzHAkEGTo_uq-",
      "title":"✮͢ꓸ⃟ꓸ⃟ꓸ✮͢পবিত্র কোরআনের ｢১১২｣ তম সুরা। এটি মক্কায় অবতীর্ণ হয়েছে। এর রুকু ｢১｣ আয়াত ｢৪｣। এই সুরায় তওহিদ বা আল্লাহর একত্ববাদের ঘোষণার পর আল্লাহর সন্তানসন্ততি আছে বলে যে ভ্রান্ত ধারণা করা হয় তার প্রতিবাদ করা হয়েছে।≛⃝⃪⋆⃝"
  },
 "Tin": {
    "url":
"https://drive.google.com/uc?id=1ga1I_dht-1WzJiq7HrV8zOqowoOG5DYP",
    "title": "✮͢ꓸ⃟ꓸ⃟ꓸ✮͢সুরাটি মক্কায় অবতীর্ণ হয়েছে। এর আয়াত সংখ্যা ｢৫৬｣টি। প্রথম আয়াতের মুদ্দাসসির শব্দ থেকে সুরাটির নামকরণ হয়েছে।≛⃝⃪⋆⃝"
 },
"Kausar": {
     "url":  "https://drive.google.com/uc?id=1gsbxC9gKujPMPw8cYbMqT6hj1oEis7G-",
    "title": "✮͢ꓸ⃟ꓸ⃟ꓸ✮͢ধর্মীয় গ্রন্থ কুরআনের ｢১০৮｣ম সূরা। এই সূরাটি মক্কায় অবতীর্ণ হয়েছে এবং এর আয়াত সংখ্যা ｢৩｣টি।≛⃝⃪⋆⃝"
},
"An-Nas": {
        "url":
"https://drive.google.com/uc?id=1gmeuc2yotx9j0da8PwmefWfSecm-ps3f",
         "title": "✮͢ꓸ⃟ꓸ⃟ꓸ✮͢ধর্মীয় গ্রন্থ কুরআনের ｢১১৪｣ তম এবং সর্বশেষ সূরা এর আয়াত অর্থাৎ বাক্য সংখ্যা ｢৬｣ এবং রূকু তথা অনুচ্ছেদ সংখ্যা ｢১｣। সূরা আন-নাস মদীনায় অবতীর্ণ হয়েছে যদিও কোন কোন বর্ণনায় একে মক্কায় অবতীর্ণ হিসাবে উল্লেখ করা হয়।≛⃝⃪⋆⃝"
},
"Quraysh": {
      "url":
"https://drive.google.com/uc?id=1h1NbXCK00omu4QWng8t7gq-2EPdQ_Wke",
       "title": "✮͢ꓸ⃟ꓸ⃟ꓸ✮͢ধর্মীয় গ্রন্থ কুরআনের ｢১০৬｣ তম সূরা। এই সূরাটি মক্কায় অবতীর্ণ হয়েছে এবং এর আয়াত সংখ্যা ｢৪｣ টি।≛⃝⃪⋆⃝"
},
"Al-Alaq": {
     "url": 
"https://drive.google.com/uc?id=1hEjyYjlq8RjW5-9_cyv7xdfUCPsaGM_G",
     "title": "✮͢ꓸ⃟ꓸ⃟ꓸ✮͢ধর্মীয় গ্রন্থ কুরআনের ｢৯৬｣ তম সূরা। সূরা আলাক্বের আয়াত সংখ্যা ｢১৯｣। এতে একটি রূকু রয়েছে।≛⃝⃪⋆⃝"
},
"Al Maun": {
    "url": 
"https://drive.google.com/uc?id=1gtSTLPQdPoPNm4-wMRLxomg2YnzJlNkt",
   "title": "✮͢ꓸ⃟ꓸ⃟ꓸ✮͢ধর্মীয় গ্রন্থ কুরআনের ｢১০৭｣ তম সূরা। এই সূরাটি মক্কায় অবতীর্ণ হয়েছে এবং এর আয়াত সংখ্যা ｢৭｣ টি। এ সূরায় কাফের ও মুনাফেকদের কতিপয় দুষ্কর্ম উল্লেখ করে তজ্জন্য জাহান্নামের শাস্তি বর্ণনা করা হয়েছে।≛⃝⃪⋆⃝ "
},
"At-Takathur": {
   "url": 
"https://drive.google.com/uc?id=1h6BRTG8WqbDSm4HXC6B_9vLfCJjJEemt",
   "title": "✮͢ꓸ⃟ꓸ⃟ꓸ✮͢ধর্মীয় গ্রন্থ কুরআনের ｢১০২｣ তম সূরা, এর আয়াত সংখ্যা ｢৮｣ টি এবং রূকুর সংখ্যা ｢১｣। আত তাকাসুর সূরাটি মক্কায় অবতীর্ণ হয়েছে। তাকাসুর শব্দটি আরবি: كثرة থেকে উদ্ভূত হয়েছে। এর অর্থ প্রচুর ধন-সম্পদ সঞ্চয় করা।≛⃝⃪⋆⃝"
},
"Al-Adiyat": {
   "url": 
"https://drive.google.com/uc?id=1h7Zk4odLRelO7z-EGN4C4hjJQTOnHho0",
   "title": "✮͢ꓸ⃟ꓸ⃟ꓸ✮͢ধর্মীয় গ্রন্থ কুরআনের ｢১০০｣ তম সূরা এর আয়াতের সংখ্যা ｢১১｣টি এর রূকুর সংখ্যা ｢১｣টি এবং ｢৩০｣ পারা। আ'দিয়াত সূরাটি মক্কায় অবতীর্ণ হয়েছে।≛⃝⃪⋆⃝"
},
"Al-Asr": {
   "url":
"https://drive.google.com/uc?id=1h5Q2U-hsV4j4RGcaEqrsYFArUN3SEv0n",
   "title": "✮͢ꓸ⃟ꓸ⃟ꓸ✮͢ধর্মীয় গ্রন্থ কুরআনের ｢১০৩｣ তম সূরা। এই সূরাটি মক্কায় অবতীর্ণ হয়েছে এবং এর আয়াত সংখ্যা ｢৩｣ টি।≛⃝⃪⋆⃝"
},
"Al-Bayyinah": {
    "url":
"https://drive.google.com/uc?id=1h9R83Albws3XVLNBGEBTWMlstP5bZDtk",
   "title": "✮͢ꓸ⃟ꓸ⃟ꓸ✮͢ধর্মীয় গ্রন্থ কুরআনের ｢৯৮｣ নম্বর সূরা, এর আয়াত সংখ্যা ｢৮｣ টি এবং এর রূকু ｢১｣। আল বাইয়্যিনাহ সূরাটি মদীনায় অবতীর্ণ হয়েছে।≛⃝⃪⋆⃝"
},
"Al-Humazah": {
   "url":
"https://drive.google.com/uc?id=1h3ieuGdACEhVV-aGodSXBjziYHt7yZF3",
    "title": "✮͢ꓸ⃟ꓸ⃟ꓸ✮͢ধর্মীয় গ্রন্থ কুরআনের ｢১০৪｣ তম সূরা। এই সূরাটি মক্কায় অবতীর্ণ হয়েছে এবং এর আয়াত সংখ্যা ｢৯｣ টি। এ সূরাটিতে তিনটি জঘন্য গোনাহের কথা বলা হয়েছে। গোনাহ্‌ তিনটি হল গীবত সামনাসামনি দোষারোপ করা ও মন্দ বলা এবং অর্থলিপ্সা।≛⃝⃪⋆⃝"
},
"Al-Qadr": {
   "url": 
"https://drive.google.com/uc?id=1hSwIPdUDpNXAkvzxPLpPLMrJeYMiUzrL",
   "title": "✮͢ꓸ⃟ꓸ⃟ꓸ✮͢ধর্মীয় গ্রন্থ কুরআনের ｢৯৭｣ তম সূরা, এর আয়াত সংখ্যা ｢৫｣ টি এবং এর রূকুর সংখ্যা ｢১｣। আল ক্বদর সূরাটি মক্কায় অবতীর্ণ হয়েছে। কদরের এর অর্থ মাহাত্ম্য ও সম্মান।≛⃝⃪⋆⃝"
},
"Az-Zalzalah": {
    "url": 
"https://drive.google.com/uc?id=1hOP3ZJryMkFBMMq2b3IcN505bpFV0BZC",
    "title": "✮͢ꓸ⃟ꓸ⃟ꓸ✮͢ধর্মীয় গ্রন্থ কুরআনের ｢৯৯｣ তম সূরা, এর আয়াত সংখ্যা ｢৮｣ টি এবং এর রূকুর সংখ্যা ｢১｣। যিলযাল সূরাটি মদিনায় অবতীর্ণ হয়েছে।≛⃝⃪⋆⃝"
},
"Falaq": {
    "url":
"https://drive.google.com/uc?id=1gpF9A1FA3VyM_oJqfr09kTK72mshv1oO",
   "title": "✮͢ꓸ⃟ꓸ⃟ꓸ✮͢ধর্মীয় গ্রন্থ কুরআনের ｢১১৩｣ তম সূরা এর আয়াত অর্থাৎ বাক্য সংখ্যা ｢৫｣ এবং রূকু তথা অনুচ্ছেদ সংখ্যা ｢১｣। সূরা আল-ফালাক মদীনায় অবতীর্ণ হয়েছে; যদিও কোন কোন বর্ণনায় একে মক্কায় অবতীর্ণ হিসাবে উল্লেখ করা হয়।≛⃝⃪⋆⃝"
},
"AL-KAHF": {
   "url": 
"https://drive.google.com/uc?id=1ggWCTGtaMx2prQky3cjz2t7spxJ3nBa1",
    "title": "✮͢ꓸ⃟ꓸ⃟ꓸ✮͢ধর্মীয় গ্রন্থ কুরআনের ｢১৮｣ তম সূরা৷ এর আয়াত সংখ্যা ｢১১০｣ টি ও রূকুর সংখ্যা ｢১২｣ টি। সূরাটি মক্কায় অবতীর্ণ হয়েছে।≛⃝⃪⋆⃝"
},
"Al-Hijr": {
   "url":
"https://drive.google.com/uc?id=17Mcb0O8NEWpTiTwsqLn9blKWGc6WsVIE",
    "title":"✮͢ꓸ⃟ꓸ⃟ꓸ✮͢এই সূরাটি মক্কায় অবতীর্ণ হয়েছে এবং এর আয়াত সংখ্যা ｢৯৯｣টি।≛⃝⃪⋆⃝"
},
"Yea Sin": {
    "url":
"https://drive.google.com/uc?id=1hfVfiiK7kowvbsVggIQNcsVTHQ3ByCyH",
    "title": "✮͢ꓸ⃟ꓸ⃟ꓸ✮͢ধর্ম-গ্রন্থ আল-কুরআনের ｢৩৬｣ তম সূরা, এর আয়াত সংখ্যা ｢৮৩｣ এবং এর রূকুর সংখ্যা ｢৫｣। সূরাটি মক্কায় অবতীর্ণ হয়েছে।≛⃝⃪⋆⃝"
},
"Rrahman": {
    "url": 
"https://drive.google.com/uc?id=1ghaNB6UrM0hjUFnKEJUg3Cf7wZ43KbOh",
    "title":"✮͢ꓸ⃟ꓸ⃟ꓸ✮͢ধর্মীয় গ্রন্থ কুরআনের ｢৫৫｣ তম সূরা; এর আয়াত অর্থাৎ বাক্য সংখ্যা ｢৭৮｣ এবং রূকু তথা অনুচ্ছেদ সংখ্যা ｢৩｣। সূরা আর রহমান মক্কায় অবতীর্ণ হয়েছে।≛⃝⃪⋆⃝"
},
"Al-Muminun": {
    "url":
"https://drive.google.com/uc?id=16cr59l1iUj3_uSja8uUYkRvbOKloE4xY",
    "title": "✮͢ꓸ⃟ꓸ⃟ꓸ✮͢ধর্মীয় গ্রন্থ কুরআনের ｢২৩｣ তম সূরা। এই সূরাটি মক্কায় অবতীর্ণ হয়েছে এবং এর আয়াত সংখ্যা ｢১১৮｣টি।≛⃝⃪⋆⃝"
},
"Al-jin":{
   "url":
"https://drive.google.com/uc?id=16og_lv7Pq1yAXxXq5HUt_VEbA5F-BW5P",
    "title": "✮͢ꓸ⃟ꓸ⃟ꓸ✮͢ধর্মীয় গ্রন্থ কুরআনের ｢৭২｣ তম সূরা; এর আয়াত অর্থাৎ বাক্য সংখ্যা ｢২৮｣ এবং রূকু তথা অনুচ্ছেদ সংখ্যা ｢২｣। সূরা আল জ্বিন মক্কায় অবতীর্ণ হয়েছে।≛⃝⃪⋆⃝"
},
"আয়াতুল কুরসি": {
   "url": 
"https://drive.google.com/uc?id=15r3dQ-hb5dsWj19Tp5e0iZZnzc-U9wuI",
    "title":"✮͢ꓸ⃟ꓸ⃟ꓸ✮͢সুরা বাক্বারাহর শুধুমাত্র ｢২৫৫｣ নাম্বার আয়াতটিকেই আয়াতুল কুরসী বলা হয় ｢২৫৬｣ নাম্বার আয়াত আয়াতুল কুরসির অন্তর্ভুক্ত নয়।≛⃝⃪⋆⃝"
},
"হাশরের শেষে ৩ আয়াত": {
    "url":
"https://drive.google.com/uc?id=160lwjUFJ-y_u__nm_m-4s9RkT09Itjwl",
    "title": "✮͢ꓸ⃟ꓸ⃟ꓸ✮͢সুরা হাশরের শেষ তিন আয়াতের আরবি বাংলা উচ্চারণ ও অর্থসহ ফজিলত সম্পর্কে একটি হাদিস। জেনে রাখা উচিত যে সুরা হাশর বা সুরা আল-হাশর পবিত্র কোরআনুল কারিমের ｢৫৯｣ নম্বর সুরা। এই সুরা মক্কায় অবতীর্ণ হয়েছে। সুরা হাশরের আয়াত সংখ্যা ｢২৪｣টি।≛⃝⃪⋆⃝"
 }
}
